xgift/__init__.py
xgift/gift.py
xgift/raw.py
xgift/utils.py
xgift-0.3.2.dist-info/licenses/LICENSE
xgift-0.3.2.dist-info/METADATA
xgift-0.3.2.dist-info/WHEEL
xgift-0.3.2.dist-info/top_level.txt
xgift-0.3.2.dist-info/RECORD
