Metadata-Version: 2.4
Name: xgift
Version: 0.3.2
Summary: Python библиотека для работы с xGift API
Author-email: aiofake <g3657775@gmail.com>
License: MIT License
Project-URL: Homepage, https://github.com/aiofake/xgift
Project-URL: Bug Tracker, https://github.com/aiofake/xgift/issues
Classifier: Programming Language :: Python :: 3
Classifier: Programming Language :: Python :: 3.8
Classifier: Programming Language :: Python :: 3.9
Classifier: Programming Language :: Python :: 3.10
Classifier: Programming Language :: Python :: 3.11
Classifier: Programming Language :: Python :: 3.12
Classifier: Operating System :: OS Independent
License-File: LICENSE
Requires-Dist: curl_cffi
Dynamic: license-file
